{
  "vhosts": [{ "name": "/" }],
  "users": [
    {
      "name": "core-user",
      "password_hash": "nVVtMZNxZd1bIpdIkfKiT2+czUY1comK/Y3cvI67NWmwZQ3n",
      "hashing_algorithm": "rabbit_password_hashing_sha256",
      "tags": "administrator"
    },
    {
      "name": "RabbitMQ_user",
      "password_hash": "8TlCHhidbiIlRvFiMvHInAoyYyA7W+zI8xddndtvRJZ5eQWi",
      "hashing_algorithm": "rabbit_password_hashing_sha256",
      "tags": "management"
    }
  ],
  "permissions": [
    {
      "user": "core-user",
      "vhost": "/",
      "configure": ".*",
      "write": ".*",
      "read": ".*"
    },
    {
      "user": "RabbitMQ_user",
      "vhost": "/",
      "configure": "^$",
      "write": ".*",
      "read": ".*"
    }
  ],
  "exchanges": [
    {
      "name": "dead-letter.exchanger",
      "vhost": "/",
      "type": "topic",
      "durable": true,
      "auto_delete": false
    },
    {
      "name": "user.event",
      "vhost": "/",
      "type": "topic",
      "durable": true,
      "auto_delete": false
    },
    {
      "name": "parameter.event",
      "vhost": "/",
      "type": "topic",
      "durable": true,
      "auto_delete": false
    },
    {
      "name": "salary.event",
      "vhost": "/",
      "type": "topic",
      "durable": true,
      "auto_delete": false
    },
    {
      "name": "curso.event",
      "vhost": "/",
      "type": "topic",
      "durable": true,
      "auto_delete": false
    },
    {
      "name": "carrera.event",
      "vhost": "/",
      "type": "topic",
      "durable": true,
      "auto_delete": false
    },
    {
      "name": "materia.event",
      "vhost": "/",
      "type": "topic",
      "durable": true,
      "auto_delete": false
    },
    {
      "name": "enrollment.event",
      "vhost": "/",
      "type": "topic",
      "durable": true,
      "auto_delete": false
    },
    {
      "name": "transaction.event",
      "vhost": "/",
      "type": "topic",
      "durable": true,
      "auto_delete": false
    },
    {
      "name": "notification.event",
      "vhost": "/",
      "type": "topic",
      "durable": true,
      "auto_delete": false
    },
    {
      "name": "item.event",
      "vhost": "/",
      "type": "topic",
      "durable": true,
      "auto_delete": false
    },
    {
      "name": "stock.event",
      "vhost": "/",
      "type": "topic",
      "durable": true,
      "auto_delete": false
    },
    {
      "name": "purchase.event",
      "vhost": "/",
      "type": "topic",
      "durable": true,
      "auto_delete": false
    },
    {
      "name": "academic-event.event",
      "vhost": "/",
      "type": "topic",
      "durable": true,
      "auto_delete": false
    },
    {
      "name": "survey.event",
      "vhost": "/",
      "type": "topic",
      "durable": true,
      "auto_delete": false
    },
    {
      "name": "attendance.event",
      "vhost": "/",
      "type": "topic",
      "durable": true,
      "auto_delete": false
    },
    {
      "name": "grade.event",
      "vhost": "/",
      "type": "topic",
      "durable": true,
      "auto_delete": false
    },
    {
      "name": "proposal.event",
      "vhost": "/",
      "type": "topic",
      "durable": true,
      "auto_delete": false
    },
    {
      "name": "act.event",
      "vhost": "/",
      "type": "topic",
      "durable": true,
      "auto_delete": false
    },
    {
      "name": "bill.event",
      "vhost": "/",
      "type": "topic",
      "durable": true,
      "auto_delete": false
    },
    {
      "name": "reservation.event",
      "vhost": "/",
      "type": "topic",
      "durable": true,
      "auto_delete": false
    },
    {
      "name": "sanctions.event",
      "vhost": "/",
      "type": "topic",
      "durable": true,
      "auto_delete": false
    }
  ],
  "queues": [
    {
      "name": "estudiante.queue",
      "vhost": "/",
      "durable": true,
      "arguments": { "x-dead-letter-exchange": "dead-letter.exchanger" }
    },
    {
      "name": "docente.queue",
      "vhost": "/",
      "durable": true,
      "arguments": { "x-dead-letter-exchange": "dead-letter.exchanger" }
    },
    {
      "name": "biblioteca.queue",
      "vhost": "/",
      "durable": true,
      "arguments": { "x-dead-letter-exchange": "dead-letter.exchanger" }
    },
    {
      "name": "comedor.queue",
      "vhost": "/",
      "durable": true,
      "arguments": { "x-dead-letter-exchange": "dead-letter.exchanger" }
    },
    {
      "name": "tienda.queue",
      "vhost": "/",
      "durable": true,
      "arguments": { "x-dead-letter-exchange": "dead-letter.exchanger" }
    },
    {
      "name": "eventos-academicos.queue",
      "vhost": "/",
      "durable": true,
      "arguments": { "x-dead-letter-exchange": "dead-letter.exchanger" }
    },
    {
      "name": "analitica.queue",
      "vhost": "/",
      "durable": true,
      "arguments": {
        "x-dead-letter-exchange": "dead-letter.exchanger",
        "x-message-ttl": 600000,
        "x-max-length": 1000
      }
    },
    {
      "name": "backoffice.queue",
      "vhost": "/",
      "durable": true,
      "arguments": { "x-dead-letter-exchange": "dead-letter.exchanger" }
    },
    {
      "name": "core.queue",
      "vhost": "/",
      "durable": true,
      "arguments": {
        "x-dead-letter-exchange": "dead-letter.exchanger",
        "x-message-ttl": 600000,
        "x-max-length": 1000
      }
    },
    { "name": "dead-letter.queue", "vhost": "/", "durable": true }
  ],
  "bindings": [
    {
      "source": "dead-letter.exchanger",
      "vhost": "/",
      "destination": "dead-letter.queue",
      "destination_type": "queue",
      "routing_key": "#"
    },
    {
      "source": "user.event",
      "vhost": "/",
      "destination": "core.queue",
      "destination_type": "queue",
      "routing_key": "#"
    },
    {
      "source": "purchase.event",
      "vhost": "/",
      "destination": "core.queue",
      "destination_type": "queue",
      "routing_key": "#"
    },
    {
      "source": "academic-event.event",
      "vhost": "/",
      "destination": "core.queue",
      "destination_type": "queue",
      "routing_key": "#"
    },
    {
      "source": "bill.event",
      "vhost": "/",
      "destination": "core.queue",
      "destination_type": "queue",
      "routing_key": "#"
    },
    {
      "source": "reservation.event",
      "vhost": "/",
      "destination": "core.queue",
      "destination_type": "queue",
      "routing_key": "#"
    },
    {
      "source": "attendance.event",
      "vhost": "/",
      "destination": "core.queue",
      "destination_type": "queue",
      "routing_key": "#"
    },
    {
      "source": "grade.event",
      "vhost": "/",
      "destination": "core.queue",
      "destination_type": "queue",
      "routing_key": "#"
    },
    {
      "source": "sanctions.event",
      "vhost": "/",
      "destination": "core.queue",
      "destination_type": "queue",
      "routing_key": "#"
    },
    {
      "source": "act.event",
      "vhost": "/",
      "destination": "core.queue",
      "destination_type": "queue",
      "routing_key": "#"
    },
    {
      "source": "salary.event",
      "vhost": "/",
      "destination": "core.queue",
      "destination_type": "queue",
      "routing_key": "#"
    },
    {
      "source": "curso.event",
      "vhost": "/",
      "destination": "backoffice.queue",
      "destination_type": "queue",
      "routing_key": "#"
    },
    {
      "source": "notification.event",
      "vhost": "/",
      "destination": "docente.queue",
      "destination_type": "queue",
      "routing_key": "#"
    },
    {
      "source": "curso.event",
      "vhost": "/",
      "destination": "docente.queue",
      "destination_type": "queue",
      "routing_key": "#"
    },
    {
      "source": "enrollment.event",
      "vhost": "/",
      "destination": "docente.queue",
      "destination_type": "queue",
      "routing_key": "#"
    },
    {
      "source": "notification.event",
      "vhost": "/",
      "destination": "estudiante.queue",
      "destination_type": "queue",
      "routing_key": "#"
    },
    {
      "source": "reservation.event",
      "vhost": "/",
      "destination": "estudiante.queue",
      "destination_type": "queue",
      "routing_key": "#"
    },
    {
      "source": "attendance.event",
      "vhost": "/",
      "destination": "estudiante.queue",
      "destination_type": "queue",
      "routing_key": "#"
    },
    {
      "source": "grade.event",
      "vhost": "/",
      "destination": "estudiante.queue",
      "destination_type": "queue",
      "routing_key": "#"
    },
    {
      "source": "purchase.event",
      "vhost": "/",
      "destination": "estudiante.queue",
      "destination_type": "queue",
      "routing_key": "#"
    },
    {
      "source": "carrera.event",
      "vhost": "/",
      "destination": "estudiante.queue",
      "destination_type": "queue",
      "routing_key": "#"
    },
    {
      "source": "materia.event",
      "vhost": "/",
      "destination": "estudiante.queue",
      "destination_type": "queue",
      "routing_key": "#"
    },
    {
      "source": "curso.event",
      "vhost": "/",
      "destination": "estudiante.queue",
      "destination_type": "queue",
      "routing_key": "#"
    },
    {
      "source": "enrollment.event",
      "vhost": "/",
      "destination": "estudiante.queue",
      "destination_type": "queue",
      "routing_key": "#"
    },
    {
      "source": "transaction.event",
      "vhost": "/",
      "destination": "estudiante.queue",
      "destination_type": "queue",
      "routing_key": "#"
    },
    {
      "source": "user.event",
      "vhost": "/",
      "destination": "estudiante.queue",
      "destination_type": "queue",
      "routing_key": "#"
    },
    {
      "source": "parameter.event",
      "vhost": "/",
      "destination": "estudiante.queue",
      "destination_type": "queue",
      "routing_key": "#"
    },
    {
      "source": "user.event",
      "vhost": "/",
      "destination": "tienda.queue",
      "destination_type": "queue",
      "routing_key": "#"
    },
    {
      "source": "transaction.event",
      "vhost": "/",
      "destination": "tienda.queue",
      "destination_type": "queue",
      "routing_key": "#"
    },
    {
      "source": "user.event",
      "vhost": "/",
      "destination": "analitica.queue",
      "destination_type": "queue",
      "routing_key": "#"
    },
    {
      "source": "parameter.event",
      "vhost": "/",
      "destination": "analitica.queue",
      "destination_type": "queue",
      "routing_key": "#"
    },
    {
      "source": "curso.event",
      "vhost": "/",
      "destination": "analitica.queue",
      "destination_type": "queue",
      "routing_key": "#"
    },
    {
      "source": "carrera.event",
      "vhost": "/",
      "destination": "analitica.queue",
      "destination_type": "queue",
      "routing_key": "#"
    },
    {
      "source": "materia.event",
      "vhost": "/",
      "destination": "analitica.queue",
      "destination_type": "queue",
      "routing_key": "#"
    },
    {
      "source": "enrollment.event",
      "vhost": "/",
      "destination": "analitica.queue",
      "destination_type": "queue",
      "routing_key": "#"
    },
    {
      "source": "transaction.event",
      "vhost": "/",
      "destination": "analitica.queue",
      "destination_type": "queue",
      "routing_key": "#"
    },
    {
      "source": "item.event",
      "vhost": "/",
      "destination": "analitica.queue",
      "destination_type": "queue",
      "routing_key": "#"
    },
    {
      "source": "stock.event",
      "vhost": "/",
      "destination": "analitica.queue",
      "destination_type": "queue",
      "routing_key": "#"
    },
    {
      "source": "purchase.event",
      "vhost": "/",
      "destination": "analitica.queue",
      "destination_type": "queue",
      "routing_key": "#"
    },
    {
      "source": "academic-event.event",
      "vhost": "/",
      "destination": "analitica.queue",
      "destination_type": "queue",
      "routing_key": "#"
    },
    {
      "source": "survey.event",
      "vhost": "/",
      "destination": "analitica.queue",
      "destination_type": "queue",
      "routing_key": "#"
    },
    {
      "source": "attendance.event",
      "vhost": "/",
      "destination": "analitica.queue",
      "destination_type": "queue",
      "routing_key": "#"
    },
    {
      "source": "grade.event",
      "vhost": "/",
      "destination": "analitica.queue",
      "destination_type": "queue",
      "routing_key": "#"
    },
    {
      "source": "proposal.event",
      "vhost": "/",
      "destination": "analitica.queue",
      "destination_type": "queue",
      "routing_key": "#"
    },
    {
      "source": "act.event",
      "vhost": "/",
      "destination": "analitica.queue",
      "destination_type": "queue",
      "routing_key": "#"
    },
    {
      "source": "bill.event",
      "vhost": "/",
      "destination": "analitica.queue",
      "destination_type": "queue",
      "routing_key": "#"
    },
    {
      "source": "reservation.event",
      "vhost": "/",
      "destination": "analitica.queue",
      "destination_type": "queue",
      "routing_key": "#"
    },
    {
      "source": "sanctions.event",
      "vhost": "/",
      "destination": "analitica.queue",
      "destination_type": "queue",
      "routing_key": "#"
    },
    {
      "source": "salary.event",
      "vhost": "/",
      "destination": "analitica.queue",
      "destination_type": "queue",
      "routing_key": "#"
    }
  ]
}
